netreport.py
netuse.c
setup.py
netdrive.egg-info/PKG-INFO
netdrive.egg-info/SOURCES.txt
netdrive.egg-info/dependency_links.txt
netdrive.egg-info/entry_points.txt
netdrive.egg-info/not-zip-safe
netdrive.egg-info/requires.txt
netdrive.egg-info/top_level.txt