Metadata-Version: 1.0
Name: netdrive
Version: 0.2.0
Summary: A tool used to report the usage of net drive in the Windows
Home-page: UNKNOWN
Author: Jondy Zhao
Author-email: jondy.zhao@nexedi.com
License: GPLv3
Keywords: netdrive
Platform: UNKNOWN
